LICENSE
MANIFEST.in
README.rst
setup.cfg
setup.py
versioneer.py
esigen/__init__.py
esigen/_pymol_server.py
esigen/_version.py
esigen/_webhooks.py
esigen/cli.py
esigen/core.py
esigen/demo.py
esigen/io.py
esigen/render.py
esigen/utils.py
esigen/web.py
esigen.egg-info/PKG-INFO
esigen.egg-info/SOURCES.txt
esigen.egg-info/dependency_links.txt
esigen.egg-info/entry_points.txt
esigen.egg-info/requires.txt
esigen.egg-info/top_level.txt
esigen/html/base.html
esigen/html/config.html
esigen/html/export.html
esigen/html/index.html
esigen/html/privacy_policy.html
esigen/html/report.html
esigen/html/static/favicon.png
esigen/html/static/uab.png
esigen/html/static/css/dropzone.css
esigen/html/static/css/font-awesome.min.css
esigen/html/static/css/github.css
esigen/html/static/css/ie8.css
esigen/html/static/css/ie9.css
esigen/html/static/css/main.css
esigen/html/static/css/noscript.css
esigen/html/static/css/images/overlay.png
esigen/html/static/fonts/FontAwesome.otf
esigen/html/static/fonts/fontawesome-webfont.eot
esigen/html/static/fonts/fontawesome-webfont.svg
esigen/html/static/fonts/fontawesome-webfont.ttf
esigen/html/static/fonts/fontawesome-webfont.woff
esigen/html/static/fonts/fontawesome-webfont.woff2
esigen/html/static/js/FileSaver.min.js
esigen/html/static/js/PIE.htc
esigen/html/static/js/clipboard.min.js
esigen/html/static/js/dropzone.min.js
esigen/html/static/js/html5shiv.js
esigen/html/static/js/jquery-2.1.4.min.js
esigen/html/static/js/jszip.js
esigen/html/static/js/jszip.min.js
esigen/html/static/js/ngl.ts2.js
esigen/html/static/js/respond.min.js
esigen/html/static/js/xepOnline.jqPlugin.js
esigen/html/static/sass/ie8.scss
esigen/html/static/sass/ie9.scss
esigen/html/static/sass/main.scss
esigen/html/static/sass/noscript.scss
esigen/html/static/sass/base/_page.scss
esigen/html/static/sass/base/_typography.scss
esigen/html/static/sass/components/_button.scss
esigen/html/static/sass/components/_form.scss
esigen/html/static/sass/components/_icon.scss
esigen/html/static/sass/components/_list.scss
esigen/html/static/sass/layout/_footer.scss
esigen/html/static/sass/layout/_main.scss
esigen/html/static/sass/layout/_wrapper.scss
