Metadata-Version: 1.1
Name: esigen
Version: 0.0.4
Summary: Generate automated reports for computational chemistry calculations
Home-page: https://github.com/insilichem/esigen
Author: Jaime Rodríguez-Guerra
Author-email: jaime.rogue@gmail.com
License: UNKNOWN
Platform: any
Classifier: Programming Language :: Python
Classifier: Development Status :: 2 - Pre-Alpha
Classifier: Natural Language :: English
Classifier: Intended Audience :: Science/Research
Classifier: Operating System :: OS Independent
Classifier: Topic :: Scientific/Engineering :: Chemistry
